{"articles":[{"CreatedAt":"2015-01-26T21:44:28Z","Vote":126,"Url":"http://www.breitbart.com/big-government/2015/01/26/exclusive-marsha-blackburn-lays-out-biggest-coming-scandal-of-2015-obamacare-data-mining/","Title":"Exclusive—Marsha Blackburn Lays Out Biggest Coming Scandal of 2015: Obamacare Data Mining","Description":"","Image":"http://media.breitbart.com/media/2015/01/AP309220344874.jpg","TweetIds":["559863206228025344"]},{"CreatedAt":"2015-01-26T00:03:42Z","Vote":57,"Url":"http://www.stitcher.com/podcast/top-traders-unplugged/e/36261435?autoplay=true","Title":"Conversations with the World’s Top CTAs, Trendfollowers \u0026 Hedge Fund Managers - Will Big Data Enable KFL to Predict the Future?","Description":"Listen to Top Traders Unplugged | Conversations with the World’s Top CTAs, Trendfollowers \u0026 Hedge Fund Managers episodes free, on demand. \"We set out to solve an enormous technology question. The technology risk on day one was very high. To some extent, it wasn’t very rational...\" - Dave Sanderson (Tweet)\nKFL Capital Management is setting out to do something every financial team on earth dreams about...\n\nThe ability to predict the future.\n\nOr at least get it right fifty four percent of the time.\n\nOur next guest on Top Traders Unplugged is the CEO and Co-Founder of KFL. In this episode we explore their trading strategy and uncover the fundamental differences between what they are doing that makes them so different from traditional alternative investment organizations.\n\nThank you for listening in on our conversation with, Dave Sanderson.\n\n\n\nSubscribe on:\n\n  \nIn This Episode, You'll Learn:\n\n\u0009The value of Battle of the Quants - Hosted by Bartt C. Kellermann\n\u0009Transitioning from commercial litigation to wholesale mutual fund vending\n\u0009How Dave Sanderson was exposed to alternative investments in the first place\n\u0009The convincing required to get top big data scientists to work on financial challenges\n\u0009The comical story of how carefully big data scientist come to conclusions\n\u0009What Dave Sanderson loves to do when he isn’t working directly on KFL Capital Management\n\u0009How Dave Sanderson sees the deviation between machine learning and systematic trading\n\u0009What it means to exist in a deluge of big data\n\u0009How Dave Sanderson and KFL perceive themselves and the usefulness of labeling\n\u0009Is machine learning a superior method than conventional approaches to trading?\n\u0009About the choice of Krystal as a name for their fund\n\u0009The structuring challenges behind KFL Capital Management and why they are more like a tech firm\n\u0009The focus for expanding KFL Capital Management\n\u0009About evolutionary computing and how KFL Capital Management grows with the markets\n\u0009Is there an environment which would be optimal for Krystal?\n\u0009Is there an environment which would be severely challenging for Krystal?\n\u0009The use of non-parametric modeling and why this type of prediction takes KFL out of most conventional finance sector buckets\n\u0009Plus much more...\n\nResources \u0026 Links Mentioned in this Episode:\n\n\u0009Attend Next Year’s 10th Anniversary of Battle of the Quants.\n\u0009Learn more about the team behind KFL Capital Management.\n\u0009Man AHL - Dave Sanderson’s initial exposure to alternative investment.\n\u0009Thomas K. Hunter - “He’s probably done more tech deals than anybody in Canada.”\n\nThis episode was sponsored by Swiss Financial Services:\n\nCo. Listen to over 25,000 radio shows, podcasts and live radio stations for free on your iPhone, iPad, Android and PC. Discover the best of news, entertainment, comedy, sports and talk radio on demand with Stitcher Radio.","Image":"http://cloudfront.assets.stitcher.com/feedimageswide/480x270_50221.jpg","TweetIds":["559501899175854080","559520610875752450","559522420889890816","559523690191142912","559528521245028352","559533945079869443","559537766199877632","559544539967270912","559557549377064960","559568906478559234","559570114765287424","559574437272367104","559578033011425282","559580237357260800","559590819125272578","559598267747799041","559614291125764097","559616113664077824","559617251104817152","559619600795852800","559625201290596352","559635531207045121","559637406123839488","559655163695480832","559657833332211713","559658849654030336","559664356515151872","559671845864374272","559675678791311361","559681328275550208","559694295998144513","559700743838392320","559702467689349120","559707008711262210","559710690051895296","559713231129026560","559724418860318720","559729562113048577","559746628975079424","559751815156469760","559752571888627712","559759522089426944","559770541889183746","559770921171689472","559788435524055040","559789201261342720","559790973853892609","559797547846598658","559804426031202305","559810321423278080","559815520351170560","559829775204642816","559839716494036992","559841515988860929","559846820512559104","559847997954326528","559862918523936769"]},{"CreatedAt":"2015-01-25T18:00:04Z","Vote":46,"Url":"https://education.emc.com/dsbook/?linkId=11832005","Title":"\u0009Data Science Book","Description":"EMC Education Services","Image":"https://education.emc.com/images/_responsive/cust/campaigns/ele/data_science_book_top_banner_image_973x300.jpg","TweetIds":["559691292201213952","559728219717656576","559804293902262272"]},{"CreatedAt":"2015-01-26T02:10:22Z","Vote":43,"Url":"http://fortune.com/2015/01/22/salesforce-ceo-marc-benioff-on-where-big-tech-is-headed/?utm_content=bufferee035\u0026utm_medium=social\u0026utm_source=twitter.com\u0026utm_campaign=buffer","Title":"Salesforce CEO Marc Benioff on where big tech is headed","Description":"We’re in the early stages of a data-science revolution, says Salesforce.com CEO Marc Benioff.","Image":"https://fortunedotcom.files.wordpress.com/2015/01/ben02_1.jpg?quality=80\u0026w=820\u0026h=570\u0026crop=1","TweetIds":["559533776494006272"]},{"CreatedAt":"2015-01-26T17:44:00Z","Vote":41,"Url":"http://hortonworks.com/blog/data-science-hadoop-predicting-airline-delays-part-3/","Title":"Predicting Airline Delays – Part 3","Description":"In this final installment of the series on Data Science and Hadoop, this blog demonstrates how to build predictive models using machine learning techniques on Hadoop.","Image":"http://hortonworks.com/wp-content/themes/hortonworks/images/layout/content/hworks_FB.png","TweetIds":["559790481467801600","559830270023847936","559768953929478144"]},{"CreatedAt":"2015-01-26T08:06:00Z","Vote":27,"Url":"http://free-ebooks.try-before-you-buy.com/2014/05/us-free-ebook-introduction-to-data.html?utm_content=buffer4fdb2\u0026utm_medium=social\u0026utm_source=twitter.com\u0026utm_campaign=buffer","Title":"Introduction to Data Science - Jeffrey M. Stanton","Description":"eBooks | Top Free eBooks - #1 source for free eBook downloads: [US]  Free Ebook | Introduction to Data Science - Jeffrey M. Stanton | Software","Image":"http://a1039.phobos.apple.com/us/r30/Publication4/v4/da/e9/9a/dae99a44-fad4-13ad-cebc-b403b9b7dcdb/BigCoverV3.170x170-75.jpg","TweetIds":["559623274607673344"]},{"CreatedAt":"2015-01-26T04:11:57Z","Vote":27,"Url":"http://www.sys-con.com/node/3284558","Title":"Event Info 2015_1: Fortinet Technical Refresher","Description":"SYS-CON Media, NJ, The world's leading i-technology media company on breaking technology news.","Image":"http://res.sys-con.com/author/13222/Nitin%20Bandugula%20150_0_0.jpg","TweetIds":["559666136921686016"]},{"CreatedAt":"2015-01-26T18:30:00Z","Vote":27,"Url":"http://www.kdnuggets.com/2015/01/deep-learning-flaws-universal-machine-learning.html?utm_source=twitterfeed\u0026utm_medium=twitter\u0026utm_campaign=Feed%3A+kdnuggets-data-mining-analytics+%28KDnuggets%3A+Data+Mining+and+Analytics%29","Title":"(Deep Learning’s Deep Flaws)’s Deep Flaws","Description":"","Image":"","TweetIds":["559780876708360192"]},{"CreatedAt":"2015-01-25T21:45:33Z","Vote":23,"Url":"http://www.opengardensblog.futuretext.com/archives/2015/01/data-science-for-iot-the-role-of-hardware-in-analytics.html#.VMVl-BJr9F0.twitter","Title":"The role of hardware in analytics","Description":"","Image":"http://pr.prchecker.info/getpr.php?codex=aHR0cDovL29wZW5nYXJkZW5zYmxvZy5mdXR1cmV0ZXh0LmNvbQ==\u0026tag=3","TweetIds":["559770216071446528"]},{"CreatedAt":"2015-01-25T15:11:54Z","Vote":23,"Url":"http://www.marketingprofs.com/opinions/2015/26884/why-machine-learning-can-help-marketers-connect-with-consumers","Title":"Why Machine Learning Can Help Marketers Connect With Consumers : MarketingProfs Article","Description":"Marketing Strategy - When applied to Big Data, machine learning can be used to predict the most effective message to serve to the right person at the right time. Here's a deeper look ...","Image":"http://i.marketingprofs.com/assets/images/opinions/machine-learning.jpg","TweetIds":["559591363956584448","559669630537834496","559682261621436418","559691412951035904","559712581129347072","559745170338766848","559766559124889601","559771808829022210","559772808691978241","559797966027100160"]},{"CreatedAt":"2015-01-25T08:04:04Z","Vote":19,"Url":"https://www.paypal-engineering.com/2015/01/12/deep-learning-on-hadoop-2-0-2/","Title":"Deep Learning on Hadoop 2.0","Description":"","Image":"https://www.paypal-engineering.com/wordpress/wp-includes/images/rss.png","TweetIds":["559751821582168064"]},{"CreatedAt":"2015-01-26T04:12:45Z","Vote":19,"Url":"http://deploy-en.newsin.tk/a/6dc84971-a3b8-11e4-bdd0-07204650040b","Title":"Niche Content Curation","Description":"Content Curation Service","Image":"","TweetIds":["559564573397622785"]},{"CreatedAt":"2015-01-26T01:20:51Z","Vote":19,"Url":"https://aws.amazon.com:443/marketplace/pp/B00RWBP7OE/ref=_ptnr_tweet","Title":"Storm \u0026 Hadoop Cluster Cloudata 1-Click Manager for Lambda Architecture on AWS Marketplace","Description":"Storm and Hadoop Cluster Cloudata 1-Click Manager for Lambda Architecture Applications, it pioneers 1-click self-provisioning and orchestration automation of Storm and Hadoop cluster for real-time, interactive","Image":"https://images-na.ssl-images-amazon.com/images/I/21ghElxghML._SX155_SY65.jpg","TweetIds":["559521316244443137","559521439913476098","559566275932721152","559566387140493314","559572079888969730","559590001017905153","559593877657894912","559596347335401472","559677444475850752","559720835276374016","559814111484461057","559816936054620160","559823538962432001","559828188990173184","559828964454064128","559830838586531840","559855752652009473","559855964640522240","559856390735667202"]},{"CreatedAt":"2015-01-26T11:17:21Z","Vote":18,"Url":"http://www.kdnuggets.com/jobs/15/01-26-flipkart-data-science-interns-data-scientists.html?utm_content=buffer5887b\u0026utm_medium=social\u0026utm_source=twitter.com\u0026utm_campaign=buffer","Title":"Data Science interns, Data Scientists","Description":"","Image":"http:///jimg/flipkart.jpg","TweetIds":["559671430346838017","559757500296482817","559770302293753857"]},{"CreatedAt":"2015-01-26T11:00:19Z","Vote":18,"Url":"http://www.kdnuggets.com/2015/01/mldas-machine-learning-data-analytics-symposium-qatar-march.html","Title":"MLDAS 2015: Machine Learning and Data Analytics Symposium – Qatar, Mar 9-10","Description":"","Image":"","TweetIds":["559750240056905729","559756951371124736","559824517208739840"]},{"CreatedAt":"2015-01-26T18:35:32Z","Vote":18,"Url":"http://i-programmer.info/bookreviews/218-data-science/8217-agile-data-science.html","Title":"Agile Data Science","Description":"Programming book reviews, programming tutorials,programming news, C#, Ruby, Python,C, C++, PHP, Visual Basic, Computer book reviews, computer history, programming history, joomla, theory, spreadsheets and more.","Image":"http://network.bemyapp.com/trk/63B24537CFFB9F87F9042022A8947FE9","TweetIds":["559783471586213889","559837331793133569","559843020645101568","559848255602044929","559853256269385728","559858450189279232","559863300755062785"]},{"CreatedAt":"2015-01-26T18:13:07Z","Vote":17,"Url":"http://www.4-traders.com/news/Debbie-Urmson-is-Named-Senior-Vice-President-of-Operations-For-UHS-America--19764313/","Title":"Debbie Urmson is Named Senior Vice President of Operations For UHS America","Description":"UHS \n      America has announced that Debbie Urmson has joined the firm as \n      Senior Vice President of Operations. Ms. Urmson is a mortgage operations \n      veteran with over...","Image":"http://www.4-traders.com/images/strat_N.png","TweetIds":["559776058468466688","559781693197131777","559787273114632193","559792860749627392","559798207937777664","559803935100522497","559809391663542272","559814978853937152","559820418660712448","559825840599351299","559831718568677376","559837328597090304","559843016194928640","559848248517877760","559853250384769024","559858443323191297","559863294442635264"]},{"CreatedAt":"2015-01-26T13:26:33Z","Vote":15,"Url":"http://101.datascience.community/2015/01/26/dataquest-free-browser-based-learning-for-data-science/","Title":"DataQuest – Free Browser-based Learning for Data Science","Description":"DataQuest is a recently launched online data science learning platform for python. The site consists of a gamified series of missions that increase in difficulty as your skills progress. Here are a few other features of the site. Sample Code Live, Interactive Browser-based Coding Environment Step by Step Instructions Instant Feedback Helpful Forums for Q\u0026A…","Image":"https://s0.wp.com/i/blank.jpg","TweetIds":["559788298093469696","559839345738514432"]},{"CreatedAt":"2015-01-26T03:40:13Z","Vote":14,"Url":"http://blogs.salesforce.com/company/2015/01/marc-benioff-the-revolution-in-data-science-will-fundamentally-change-how-we-run-our-business.html?d=70130000000tUX4","Title":"Marc Benioff: \"The Revolution in Data Science Will Fundamentally Change How We Run Our Business\"","Description":"Salesforce CEO Marc Benioff is known for being a visionary — and today, in an interview with Fortune, he gave us a preview of his vision for the future of technology and business. “We’re in an AI spring,” Benioff told Fortune’s Adam Lashinsky. “For our company, and I think for...","Image":"http://blogs.salesforce.com/.a/6a00e54ee3905b883301bb07e047fb970d-200wi","TweetIds":["559770530979389440","559792545459208192"]},{"CreatedAt":"2015-01-26T20:54:48Z","Vote":14,"Url":"http://www.infoworld.com/article/2871935/application-development/infoworlds-2015-technology-of-the-year-award-winners.html?utm_campaign=Press%20Releases\u0026utm_content=11566221\u0026utm_medium=social\u0026utm_source=twitter","Title":"InfoWorld's 2015 Technology of the Year Award winners","Description":"InfoWorld picks the best hardware, software, development tools, and cloud services of the year","Image":"http://images.techhive.com/images/article/2015/01/toy15-primary-100563439-carousel.idge.jpg","TweetIds":["559817682410041345"]}]}